wavelinknextcord/__init__.py
wavelinknextcord/backoff.py
wavelinknextcord/enums.py
wavelinknextcord/exceptions.py
wavelinknextcord/ext/spotify/__init__.py
wavelinknextcord/filters.py
wavelinknextcord/node.py
wavelinknextcord/payloads.py
wavelinknextcord/player.py
wavelinknextcord/queue.py
wavelinknextcord/tracks.py
wavelinknextcord/types/events.py
wavelinknextcord/types/request.py
wavelinknextcord/types/state.py
wavelinknextcord/types/track.py
wavelinknextcord/websocket.py
wavelinknextcord-1.0.0.dist-info/METADATA
wavelinknextcord-1.0.0.dist-info/WHEEL
wavelinknextcord-1.0.0.dist-info/RECORD
